<xml xmlns:o="urn:schemas-microsoft-com:office:office">
 <o:MainFile HRef="../RPM_YUM_Oct-Jan_2020.htm"/>
 <o:File HRef="themedata.thmx"/>
 <o:File HRef="colorschememapping.xml"/>
 <o:File HRef="image001.png"/>
 <o:File HRef="oledata.mso"/>
 <o:File HRef="image002.png"/>
 <o:File HRef="image003.png"/>
 <o:File HRef="image014.jpg"/>
 <o:File HRef="image005.jpg"/>
 <o:File HRef="image006.png"/>
 <o:File HRef="image007.png"/>
 <o:File HRef="image015.jpg"/>
 <o:File HRef="image009.png"/>
 <o:File HRef="image016.jpg"/>
 <o:File HRef="image011.png"/>
 <o:File HRef="image017.jpg"/>
 <o:File HRef="header.htm"/>
 <o:File HRef="image013.jpg"/>
 <o:File HRef="filelist.xml"/>
</xml>